[
  {
    "route": "Route Cuttack - 1 (A) & 2 (A)",
    "stops": [
      { "name": "Trisulia", "lat": 20.4363, "lng": 85.8314 },
      { "name": "CDA Naibandha", "lat": 20.4840, "lng": 85.8350 },
      { "name": "CDA Bijupattnaik Park", "lat": 20.4851, "lng": 85.8504 },
      { "name": "SBI Sqr", "lat": 20.4780, "lng": 85.8620 },
      { "name": "Dahibara Sqr", "lat": 20.4765, "lng": 85.8640 },
      { "name": "Justic Sqr", "lat": 20.4735, "lng": 85.8687 },
      { "name": "CDA Petanala", "lat": 20.4700, "lng": 85.8700 },
      { "name": "CDA-9 (Saraswati School)", "lat": 20.4682, "lng": 85.8751 },
      { "name": "CDA-9", "lat": 20.4670, "lng": 85.8770 },
      { "name": "CDA-9 (Ganesh Palace)", "lat": 20.4655, "lng": 85.8795 },
      { "name": "CDA-6 (Marcket Complex)", "lat": 20.4610, "lng": 85.8820 },
      { "name": "CDA - 6 (Lal Chand)", "lat": 20.4590, "lng": 85.8845 },
      { "name": "CDA-6 (JP Park)", "lat": 20.4570, "lng": 85.8870 },
      { "name": "CDA - 6 (Patra Electronic)", "lat": 20.4550, "lng": 85.8890 },
      { "name": "Aswini Hospital", "lat": 20.4501, "lng": 85.8856 },
      { "name": "Satichaura", "lat": 20.4611, "lng": 85.8685 },
      { "name": "Judicial", "lat": 20.4645, "lng": 85.8722 },
      { "name": "High Court", "lat": 20.4624, "lng": 85.8752 },
      { "name": "Puri Ghat", "lat": 20.4560, "lng": 85.8795 },
      { "name": "Jhanjir Mangala Gada", "lat": 20.4533, "lng": 85.8833 },
      { "name": "Khan Nagar (Traffic)", "lat": 20.4485, "lng": 85.8842 },
      { "name": "Badambadi", "lat": 20.4570, "lng": 85.8820 },
      { "name": "AD Marcket", "lat": 20.4550, "lng": 85.8850 },
      { "name": "Link Road", "lat": 20.4430, "lng": 85.8943 },
      { "name": "Press Chhaka", "lat": 20.4357, "lng": 85.9015 },
      { "name": "Gopalpur", "lat": 20.4285, "lng": 85.9056 },
      { "name": "Balikuda", "lat": 20.4172, "lng": 85.9050 },
      { "name": "BMW Showroom (S Thana)", "lat": 20.3950, "lng": 85.9000 },
      { "name": "Pratap Nagari (Dakulei Pitha)", "lat": 20.3776, "lng": 85.8923 },
      { "name": "Nakhara", "lat": 20.3680, "lng": 85.8810 },
      { "name": "Pahala", "lat": 20.3345, "lng": 85.8613 },
      { "name": "ITER", "lat": 20.2496, "lng": 85.8002 }
    ]
  },
  {
    "route": "Route Cuttack - 1 (C) & 2 (C)",
    "stops": [
      { "name": "Krushak Bazar", "lat": 20.4611, "lng": 85.8685 },
      { "name": "Bidanasi", "lat": 20.4845, "lng": 85.8315 },
      { "name": "Chahata", "lat": 20.4860, "lng": 85.8580 },
      { "name": "Dearpark", "lat": 20.4820, "lng": 85.8720 },
      { "name": "Cantenment Thana", "lat": 20.4795, "lng": 85.8785 },
      { "name": "Baliyatra Padia", "lat": 20.4825, "lng": 85.8830 },
      { "name": "Mata Matha", "lat": 20.4880, "lng": 85.8900 },
      { "name": "Jobra", "lat": 20.4905, "lng": 85.8980 },
      { "name": "Haramani Mandap", "lat": 20.4890, "lng": 85.9080 },
      { "name": "Mahanadi Vihar Bus Stand", "lat": 20.4810, "lng": 85.9180 },
      { "name": "Mahanadi Vihar Mangala Mandir", "lat": 20.4780, "lng": 85.9220 },
      { "name": "Sikharpur", "lat": 20.4680, "lng": 85.9280 },
      { "name": "Gandar Pur", "lat": 20.4630, "lng": 85.9320 },
      { "name": "OMP", "lat": 20.4530, "lng": 85.9250 },
      { "name": "Puri Canalroad", "lat": 20.3480, "lng": 85.8680 },
      { "name": "Hansapal", "lat": 20.3220, "lng": 85.8520 },
      { "name": "Saptasati Vihar", "lat": 20.3150, "lng": 85.8450 },
      { "name": "Palasuni", "lat": 20.3080, "lng": 85.8380 },
      { "name": "Nayapalli", "lat": 20.2882, "lng": 85.8155 },
      { "name": "CRP", "lat": 20.2835, "lng": 85.8115 },
      { "name": "ITER", "lat": 20.2496, "lng": 85.8002 }
    ]
  },
  {
    "route": "Route Patia 1 (A) & 2 (A)",
    "stops": [
      { "name": "Dash Pur", "lat": 20.3800, "lng": 85.8000 },
      { "name": "Chandaka", "lat": 20.4005, "lng": 85.7667 },
      { "name": "Sikharchandi", "lat": 20.3582, "lng": 85.8155 },
      { "name": "KIIT", "lat": 20.3541, "lng": 85.8189 },
      { "name": "Raghunath Pur", "lat": 20.3650, "lng": 85.8200 },
      { "name": "Subhadra Apprtment", "lat": 20.3600, "lng": 85.8220 },
      { "name": "Patia (Bigbazar)", "lat": 20.3475, "lng": 85.8159 },
      { "name": "Kanan Vihar", "lat": 20.3412, "lng": 85.8154 },
      { "name": "Patia", "lat": 20.3450, "lng": 85.8160 },
      { "name": "Shree Vihar", "lat": 20.3350, "lng": 85.8150 },
      { "name": "D Amana", "lat": 20.3255, "lng": 85.8152 },
      { "name": "CS Pur Petrol Pump", "lat": 20.3185, "lng": 85.8157 },
      { "name": "Omfed Square", "lat": 20.3120, "lng": 85.8165 },
      { "name": "Nalco Chhak", "lat": 20.3090, "lng": 85.8181 },
      { "name": "Pal Hight", "lat": 20.3015, "lng": 85.8170 },
      { "name": "Jaydevvihar", "lat": 20.3012, "lng": 85.8170 },
      { "name": "New AG Colony", "lat": 20.2950, "lng": 85.8180 },
      { "name": "Old The World Square", "lat": 20.2900, "lng": 85.8200 },
      { "name": "Sastri Nagar", "lat": 20.2845, "lng": 85.8142 },
      { "name": "Unit 8 DAV", "lat": 20.2801, "lng": 85.8085 },
      { "name": "Passport Office", "lat": 20.2750, "lng": 85.8050 },
      { "name": "Stuwart School", "lat": 20.2700, "lng": 85.8000 },
      { "name": "Delta", "lat": 20.2652, "lng": 85.7981 },
      { "name": "Soubhagya Nagar", "lat": 20.2615, "lng": 85.7932 },
      { "name": "ITER", "lat": 20.2496, "lng": 85.8002 }
    ]
  },
  {
    "route": "Route Patia 1 (B) & 2 (B)",
    "stops": [
      { "name": "Sailashree Vihar", "lat": 20.3342, "lng": 85.8092 },
      { "name": "Niladri Vihar", "lat": 20.3340, "lng": 85.8055 },
      { "name": "Damana", "lat": 20.3255, "lng": 85.8152 },
      { "name": "Railway Stadium", "lat": 20.3195, "lng": 85.8202 },
      { "name": "Mancheswar", "lat": 20.3150, "lng": 85.8450 },
      { "name": "Sainik School", "lat": 20.3105, "lng": 85.8305 },
      { "name": "Press Square", "lat": 20.3060, "lng": 85.8260 },
      { "name": "Railvihar", "lat": 20.3172, "lng": 85.8125 },
      { "name": "Xavieer", "lat": 20.3051, "lng": 85.8158 },
      { "name": "Mayfair", "lat": 20.2985, "lng": 85.8115 },
      { "name": "Biju Pattnaik College", "lat": 20.2950, "lng": 85.8050 },
      { "name": "Ekamra Sai Mandir", "lat": 20.2900, "lng": 85.8000 },
      { "name": "CRPF", "lat": 20.2848, "lng": 85.7952 },
      { "name": "Rental Colony", "lat": 20.2805, "lng": 85.7895 },
      { "name": "KV School-2", "lat": 20.2750, "lng": 85.7850 },
      { "name": "Fire Station", "lat": 20.2762, "lng": 85.8118 },
      { "name": "Baramunda", "lat": 20.2705, "lng": 85.7955 },
      { "name": "ITER", "lat": 20.2496, "lng": 85.8002 }
    ]
  },
  {
    "route": "Route Utara 1 (A) & 2 (A)",
    "stops": [
      { "name": "Gudia Pokhari", "lat": 20.1800, "lng": 85.8400 },
      { "name": "Uttara", "lat": 20.2000, "lng": 85.8450 },
      { "name": "Dhauli Chhaka", "lat": 20.2100, "lng": 85.8400 },
      { "name": "Lingipur", "lat": 20.2200, "lng": 85.8400 },
      { "name": "Nuagaon", "lat": 20.2250, "lng": 85.8350 },
      { "name": "Samantara Pur", "lat": 20.2300, "lng": 85.8350 },
      { "name": "Garage Chhak", "lat": 20.2350, "lng": 85.8350 },
      { "name": "Rabi Talkies", "lat": 20.2400, "lng": 85.8350 },
      { "name": "Raja Rani", "lat": 20.2400, "lng": 85.8400 },
      { "name": "Chilli Pokhari", "lat": 20.2450, "lng": 85.8400 },
      { "name": "Radhika Tower", "lat": 20.2500, "lng": 85.8400 },
      { "name": "Brahmeswar", "lat": 20.2550, "lng": 85.8450 },
      { "name": "Tankapani Bridge", "lat": 20.2600, "lng": 85.8500 },
      { "name": "Badagada", "lat": 20.2550, "lng": 85.8350 },
      { "name": "BJEM School", "lat": 20.2500, "lng": 85.8300 },
      { "name": "Kalpana", "lat": 20.2600, "lng": 85.8350 },
      { "name": "Old Station", "lat": 20.2650, "lng": 85.8400 },
      { "name": "Rabitalkies", "lat": 20.2400, "lng": 85.8350 },
      { "name": "Vivekananda Marg", "lat": 20.2500, "lng": 85.8250 },
      { "name": "Mausima", "lat": 20.2500, "lng": 85.8200 },
      { "name": "Sishubhaban", "lat": 20.2550, "lng": 85.8250 },
      { "name": "New Forest Park", "lat": 20.2500, "lng": 85.8150 },
      { "name": "Palaspali (Navin Nivas)", "lat": 20.2450, "lng": 85.8100 },
      { "name": "Bhim Tangi Road", "lat": 20.2400, "lng": 85.8050 },
      { "name": "Lingaraj Station Sqr", "lat": 20.2350, "lng": 85.8100 },
      { "name": "Pokhariput Sqr", "lat": 20.2400, "lng": 85.8000 },
      { "name": "ITER", "lat": 20.2496, "lng": 85.8002 }
    ]
  },
  {
    "route": "Route Kesura 1 (A) & 2 (A)",
    "stops": [
      { "name": "VSS Nagar (Kalyani Mandap)", "lat": 20.3150, "lng": 85.8350 },
      { "name": "VSS Nagar", "lat": 20.3100, "lng": 85.8300 },
      { "name": "Chakeisiani", "lat": 20.3150, "lng": 85.8400 },
      { "name": "Rasulgarh", "lat": 20.3005, "lng": 85.8450 },
      { "name": "GGP Chowk", "lat": 20.2950, "lng": 85.8500 },
      { "name": "Pandra", "lat": 20.2900, "lng": 85.8550 },
      { "name": "Kesura Mangaraj Point", "lat": 20.2850, "lng": 85.8500 },
      { "name": "Jagannath Nagar", "lat": 20.2800, "lng": 85.8450 },
      { "name": "Jharapara (Ganesh Pandap)", "lat": 20.2768, "lng": 85.8621 },
      { "name": "Jharapara", "lat": 20.2768, "lng": 85.8621 },
      { "name": "Laxmi Sagar", "lat": 20.2750, "lng": 85.8450 },
      { "name": "Cuttack Road", "lat": 20.2800, "lng": 85.8400 },
      { "name": "Bomikhal", "lat": 20.2850, "lng": 85.8350 },
      { "name": "Vanivihar", "lat": 20.3013, "lng": 85.8335 },
      { "name": "Rupali Sqr", "lat": 20.2900, "lng": 85.8350 },
      { "name": "Saheed Nagar", "lat": 20.2850, "lng": 85.8350 },
      { "name": "Nicco Park", "lat": 20.2800, "lng": 85.8300 },
      { "name": "Unit-9", "lat": 20.2800, "lng": 85.8250 },
      { "name": "Kalimadir", "lat": 20.2750, "lng": 85.8250 },
      { "name": "Ram Mandir", "lat": 20.2750, "lng": 85.8350 },
      { "name": "Keshari Talkies", "lat": 20.2700, "lng": 85.8300 },
      { "name": "Master Canteen", "lat": 20.2650, "lng": 85.8350 },
      { "name": "Raj Mahal Square", "lat": 20.2600, "lng": 85.8300 },
      { "name": "Ganga Nagar", "lat": 20.2650, "lng": 85.8150 },
      { "name": "Governor House", "lat": 20.2700, "lng": 85.8100 },
      { "name": "Gopabandhu Square", "lat": 20.2750, "lng": 85.8150 },
      { "name": "ITER", "lat": 20.2496, "lng": 85.8002 }
    ]
  },
  {
    "route": "Route Khordha 1 (A) & 2 (A)",
    "stops": [
      { "name": "Chandi Square", "lat": 20.1800, "lng": 85.6200 },
      { "name": "Khordha Old Bus Stand", "lat": 20.1850, "lng": 85.6250 },
      { "name": "Khordha New Bus Stand", "lat": 20.1900, "lng": 85.6300 },
      { "name": "Colecter Square", "lat": 20.1950, "lng": 85.6350 },
      { "name": "Barunei Industrial", "lat": 20.1800, "lng": 85.6400 },
      { "name": "Khordha By-Pass", "lat": 20.1850, "lng": 85.6500 },
      { "name": "Badatota (Jatani Road)", "lat": 20.1700, "lng": 85.6600 },
      { "name": "NISER Sqr", "lat": 20.1550, "lng": 85.6700 },
      { "name": "Hari Bahina Sqr", "lat": 20.1600, "lng": 85.6800 },
      { "name": "Sitaram Sqr", "lat": 20.1650, "lng": 85.6900 },
      { "name": "Jatani Medical", "lat": 20.1700, "lng": 85.7000 },
      { "name": "Centurian", "lat": 20.1750, "lng": 85.7100 },
      { "name": "Jatani Gate", "lat": 20.1800, "lng": 85.7200 },
      { "name": "Gohira", "lat": 20.2000, "lng": 85.7300 },
      { "name": "Tamando", "lat": 20.2200, "lng": 85.7500 },
      { "name": "Kalinga Vihar", "lat": 20.2378, "lng": 85.7936 },
      { "name": "Patrapada", "lat": 20.2500, "lng": 85.7700 },
      { "name": "Aiginia", "lat": 20.2550, "lng": 85.7800 },
      { "name": "AMRI (Manipal Hospital)", "lat": 20.2600, "lng": 85.7850 },
      { "name": "Kalinga Nagar", "lat": 20.2650, "lng": 85.7900 },
      { "name": "IGKC Hospital", "lat": 20.2650, "lng": 85.7950 },
      { "name": "Nuagaon Chhak", "lat": 20.2700, "lng": 85.7950 },
      { "name": "Gothapatana", "lat": 20.2942, "lng": 85.7444 },
      { "name": "SUM Hospital", "lat": 20.2850, "lng": 85.7750 },
      { "name": "ITER", "lat": 20.2496, "lng": 85.8002 }
    ]
  }
]
